{
"layer_geom_type_s": "Mixed", 
"layer_modified_dt": "2017-03-10T15:33:10Z", 
"solr_geom": "ENVELOPE(-90.312529, -89.59926, 43.644499, 43.146814)", 
"dct_references_s": "{\"http://schema.org/url\":\"http://saukgis.maps.arcgis.com/home/index.html\",\"http://schema.org/downloadUrl\":\"https://gisdata.wisc.edu/public/Sauk_Roads_2016.zip\",\"http://www.isotc211.org/schemas/2005/gmd/\":\"https://opengeometadata.github.io/big-ten/b1/d6/7d/7cc3c04903beb6022e3a8795b8/iso19139.xml\"}", 
"dc_rights_s": "Public", 
"uuid": "b1d67d7c-c3c0-4903-beb6-022e3a8795b8", 
"dct_provenance_s": "Wisconsin", 
"dc_subject_sm": [
"Transportation", 
"Roads", 
"Streets"
], 
"dct_temporal_sm": "2016", 
"dc_description_s": "This line data layer represents roads for Sauk County, Wisconsin in 2016. It is a feature class within the geodatabase, Sauk_Roads_2016.gdb.[This feature class contains detailed line work supporting Sauk Counties road network and contains street name, classification, and address range attributes]", 
"dct_issued_s": "2016-06-01", 
"dc_format_s": "Geodatabase", 
"dc_creator_sm": [
"Sauk County Land Information/GIS Department"
], 
"dc_type_s": "Dataset", 
"dc_identifier_s": "b1d67d7c-c3c0-4903-beb6-022e3a8795b8", 
"georss_polygon_s": "43.146814 -90.312529 43.644499 -90.312529 43.644499 -89.59926 43.146814 -89.59926 43.146814 -90.312529", 
"solr_year_i": 2016, 
"dct_spatial_sm": [
"Sauk County, Wisconsin, United States", 
"Wisconsin, United States"
], 
"layer_id_s": "Sauk_Roads_2016_arc", 
"georss_box_s": "43.146814 -90.312529 43.644499 -89.59926", 
"dc_title_s": "Roads Sauk County, Wisconsin 2016", 
"layer_slug_s": "b1d67d7c-c3c0-4903-beb6-022e3a8795b8", 
"dct_isPartOf_sm": "Wisconsin Counties Open Data"
}