{
"layer_geom_type_s": "Mixed", 
"layer_modified_dt": "2017-04-05T13:35:11Z", 
"solr_geom": "ENVELOPE(-95.806, -90.4642, 41.7207, 41.2575)", 
"dct_references_s": "{\"http://schema.org/url\":\"http://public.iowadot.opendata.arcgis.com/datasets/039a8cf7debf4c55abdb2aef849060bf_2\",\"http://www.isotc211.org/schemas/2005/gmd/\":\"https://opengeometadata.github.io/big-ten/5b/e8/2e/d3aae64f0ab6e10c584086f57d/iso19139.xml\",\"urn:x-esri:serviceType:ArcGIS#FeatureLayer\":\"https://services.arcgis.com/8lRhdTsQyJpO52F1/ArcGIS/rest/services/I80PELResources/FeatureServer/2\",\"http://schema.org/downloadUrl\":\"http://public.iowadot.opendata.arcgis.com/datasets/039a8cf7debf4c55abdb2aef849060bf_2.zip\"}", 
"dc_rights_s": "Public", 
"uuid": "5be82ed3-aae6-4f0a-b6e1-0c584086f57d", 
"dct_provenance_s": "Iowa", 
"dc_subject_sm": [
"Transportation"
], 
"dct_temporal_sm": "2016", 
"dc_description_s": "This map shows known or potential wetland resources within the I-80 Planning and Environmental Linkage (PEL) Study Area. The Planning and Environmental Linkage (PEL) study is being conducted by the Office of Location and Environment.", 
"dct_issued_s": "2016-06-16", 
"dc_format_s": "Shapefile", 
"dc_creator_sm": [
"Iowa Department of Transportation"
], 
"dc_type_s": "Dataset", 
"dc_identifier_s": "5be82ed3-aae6-4f0a-b6e1-0c584086f57d", 
"georss_polygon_s": "41.2575 -95.806 41.7207 -95.806 41.7207 -90.4642 41.2575 -90.4642 41.2575 -95.806", 
"solr_year_i": 2016, 
"dct_spatial_sm": [
"Iowa, United States"
], 
"dc_publisher_sm": [
"Iowa DOT Open Data Portal"
], 
"layer_id_s": "I80PELResourcesWetlands_shp", 
"georss_box_s": "41.2575 -95.806 41.7207 -90.4642", 
"dc_title_s": "I-80 Planning and Environmental Linkage (PEL) Resources - Wetlands: Iowa", 
"layer_slug_s": "5be82ed3-aae6-4f0a-b6e1-0c584086f57d", 
"dct_isPartOf_sm": "Iowa Department of Transportation (DOT)"
}