{
"layer_geom_type_s": "Point", 
"layer_modified_dt": "2017-04-05T15:21:46Z", 
"solr_geom": "ENVELOPE(-79.4496, -75.138, 39.6306, 38.0095)", 
"dct_references_s": "{\"http://schema.org/downloadUrl\":\"http://data.imap.maryland.gov/datasets/9adb03d9ff794377bd8e13a7e41338f4_38.zip\",\"http://www.isotc211.org/schemas/2005/gmd/\":\"https://opengeometadata.github.io/big-ten/ef/28/e9/928c804a97bdf793fb3cd6fe6e/iso19139.xml\",\"urn:x-esri:serviceType:ArcGIS#FeatureLayer\":\"https://geodata.md.gov/imap/rest/services/Society/MD_SportVenues/FeatureServer/38\",\"http://schema.org/url\":\"http://data.imap.maryland.gov/datasets/9adb03d9ff794377bd8e13a7e41338f4_38\"}", 
"dc_rights_s": "Public", 
"uuid": "ef28e992-8c80-4a97-bdf7-93fb3cd6fe6e", 
"dct_provenance_s": "Maryland", 
"dc_subject_sm": [
"Society", 
"Sports"
], 
"dct_temporal_sm": "2016", 
"dc_description_s": "Maryland Sports (http://www.marylandsports.us/) has identified sport venues located within the State of Maryland. These venues offer opportunities to participate in free and fee-based, organized and pick-up, indoor and outdoor sports and physical fitness related activities in the area of Kayaking.Last Updated: 08/2014Feature Service Layer Link:http://geodata.md.gov/imap/rest/services/Society/MD_SportVenues/FeatureServer/38", 
"dct_issued_s": "2016-02-17T14:06:59.000ZZ", 
"dc_format_s": "Shapefile", 
"dc_creator_sm": [
"ArcGIS Online for Maryland"
], 
"dc_type_s": "Dataset", 
"dc_identifier_s": "ef28e992-8c80-4a97-bdf7-93fb3cd6fe6e", 
"georss_polygon_s": "38.0095 -79.4496 39.6306 -79.4496 39.6306 -75.138 38.0095 -75.138 38.0095 -79.4496", 
"solr_year_i": 2016, 
"dct_spatial_sm": [
"Maryland, United States"
], 
"dc_publisher_sm": [], 
"layer_id_s": "ef28e992-8c80-4a97-bdf7-93fb3cd6fe6e", 
"georss_box_s": "38.0095 -79.4496 39.6306 -75.138", 
"dc_title_s": "Sport Venues - Kayaking: Maryland, 2016", 
"layer_slug_s": "ef28e992-8c80-4a97-bdf7-93fb3cd6fe6e", 
"dct_isPartOf_sm": "Maryland iMap"
}