{
"layer_geom_type_s": "Polygon", 
"layer_modified_dt": "2017-01-11T00:00:00Z", 
"solr_geom": "ENVELOPE(-88.436636, -87.469043, 45.797615, 44.933548)", 
"dct_references_s": "{\"http://schema.org/downloadUrl\":\"https://gisdata.wisc.edu/public/Marinette_Hydro_2017.zip\",\"http://www.isotc211.org/schemas/2005/gmd/\":\"https://opengeometadata.github.io/big-ten/a2/b1/d4/cfcfb64890a01ffc7c08f73209/iso19139.xml\"}", 
"dc_rights_s": "Public", 
"uuid": "A2B1D4CF-CFB6-4890-A01F-FC7C08F73209", 
"dct_provenance_s": "Wisconsin", 
"dc_subject_sm": [
"Inland Waters", 
"Polygon", 
"Hydrography"
], 
"dct_temporal_sm": "2017", 
"dc_description_s": "These polygon and line data layers represent hydrography for Marinette County, Wisconsin in 2017. They are feature classes within the geodatabase Marinette_Hydro_2017.gdb. The features included in this geodatabase are 'HydroArc_2017' and 'HydroPoly_2017'.", 
"dct_issued_s": "2017-03-16", 
"dc_format_s": "Geodatabase", 
"dc_creator_sm": [
"Marinette County Land Information Office"
], 
"dc_type_s": "Dataset", 
"dc_identifier_s": "A2B1D4CF-CFB6-4890-A01F-FC7C08F73209", 
"georss_polygon_s": "44.933548 -88.436636 45.797615 -88.436636 45.797615 -87.469043 44.933548 -87.469043 44.933548 -88.436636", 
"solr_year_i": 2017, 
"dct_spatial_sm": [
"Wisconsin, United States", 
"Marinette County, Wisconsin, United States"
], 
"layer_id_s": "A2B1D4CF-CFB6-4890-A01F-FC7C08F73209", 
"georss_box_s": "44.933548 -88.436636 45.797615 -87.469043", 
"dc_title_s": "Hydro: (Polygon and Line) Marinette County, Wisconsin, 2017", 
"layer_slug_s": "A2B1D4CF-CFB6-4890-A01F-FC7C08F73209", 
"dct_isPartOf_sm": "Wisconsin Counties Open Data"
}