{
"layer_geom_type_s": "Mixed", 
"layer_modified_dt": "2016-08-01T13:58:35Z", 
"solr_geom": "ENVELOPE(-80.51934, -74.69392, 42.26501, 39.71987)", 
"dct_references_s": "{\"http://schema.org/url\":\"http://www.pasda.psu.edu/uci/DataSummary.aspx?dataset=1038\",\"http://www.isotc211.org/schemas/2005/gmd/\":\"https://opengeometadata.github.io/big-ten/79/e6/82/b1a1544195b78ea541562a130b/iso19139.xml\"}", 
"dc_rights_s": "Public", 
"uuid": "79e682b1-a154-4195-b78e-a541562a130b", 
"dct_provenance_s": "Penn State", 
"dc_subject_sm": [
"Transportation"
], 
"dct_temporal_sm": "2016", 
"dc_description_s": "Public roads within Pennsylvania. This file includes all identified public roads not maintained by the PA Dept. of Transportation.", 
"dct_issued_s": "2016-01-01", 
"dc_format_s": "File", 
"dc_creator_sm": [
"Pennsylvania Department of Transportation, Bureau of Planning and Research, Geographic Information Division"
], 
"dc_type_s": "Dataset", 
"dc_identifier_s": "79e682b1-a154-4195-b78e-a541562a130b", 
"georss_polygon_s": "39.71987 -80.51934 42.26501 -80.51934 42.26501 -74.69392 39.71987 -74.69392 39.71987 -80.51934", 
"solr_year_i": 2016, 
"dct_spatial_sm": [
"Pennsylvania, United States"
], 
"layer_id_s": "PaLocalRoads2016_01", 
"georss_box_s": "39.71987 -80.51934 42.26501 -74.69392", 
"dc_title_s": "Pennsylvania local roads: Pennsylvania, 2016", 
"layer_slug_s": "79e682b1-a154-4195-b78e-a541562a130b", 
"dct_isPartOf_sm": "Pennsylvania Spatial Data Access (PASDA)"
}