{
  "geoblacklight_version": "1.0",
  "dc_rights_s": "Public",
  "layer_modified_dt": "2020-01-30T17:05:08Z",
  "dc_identifier_s": "AC297122-1488-4824-9D05-714D5AFDE5B4",
  "dc_title_s": "Zoning: Racine County, Wisconsin, 2015",
  "dc_description_s": "This data layer represents zoning for Racine County, Wisconsin in 2015.",
  "dc_creator_sm": [
    "Racine County, Wisconsin"
  ],
  "dc_publisher_sm": [
    ""
  ],
  "dc_subject_sm": [
    "Planning and Cadastral"
  ],
  "dc_format_s": "Shapefile",
  "layer_geom_type_s": "Polygon",
  "dct_provenance_s": "Wisconsin",
  "dct_issued_s": "",
  "dct_temporal_sm": [
    "2015"
  ],
  "solr_year_i": "2015",
  "dct_spatial_sm": [
    "Racine County, Wisconsin",
    "Wisconsin"
  ],
  "solr_geom": "ENVELOPE(-88.30794,-87.757617,42.843609,42.610759)",
  "dc_language_sm": [
    "English"
  ],
  "b1g_code_s": "10d",
  "dct_references_s": "{\"http://schema.org/downloadUrl\":\"https://gisdata.wisc.edu/public/Racine_Zoning_2015.zip\",\"http://schema.org/url\":\"http://data-racinecounty.opendata.arcgis.com/\",\"http://www.isotc211.org/schemas/2005/gmd/\":\"https://gisdata.wisc.edu/public/metadata/Racine_Zoning_2015.xml\"}",
  "b1g_image_ss": ""
}