{
  "geoblacklight_version": "1.0",
  "dc_rights_s": "Public",
  "layer_modified_dt": "2020-01-30T17:05:08Z",
  "dc_identifier_s": "C372814B-6348-49FA-81FD-0054A41EF3C1",
  "dc_title_s": "Municipalities: Marinette County, Wisconsin, 2014",
  "dc_description_s": "This data layer represents municipalities for Marinette County, Wisconsin in 2014. [The municipal boundary feature class represents the civil/municipal boundaries in Marinette County, Wisconsin. Data is referenced to the Marinette County Coordinate System, North American Datum 1983 with the 1991 adjustment (NAD83/91).]",
  "dc_creator_sm": [
    "Marinette County, Wisconsin"
  ],
  "dc_publisher_sm": [
    ""
  ],
  "dc_subject_sm": [
    "Boundaries"
  ],
  "dc_format_s": "Shapefile",
  "layer_geom_type_s": "Polygon",
  "dct_provenance_s": "Wisconsin",
  "dct_issued_s": "",
  "dct_temporal_sm": [
    "2014"
  ],
  "solr_year_i": "2014",
  "dct_spatial_sm": [
    "Marinette County, Wisconsin",
    "Wisconsin"
  ],
  "solr_geom": "ENVELOPE(-88.433421,-87.487301,45.796011,44.963868)",
  "dc_language_sm": [
    "English"
  ],
  "b1g_code_s": "10d",
  "dct_references_s": "{\"http://schema.org/downloadUrl\":\"https://gisdata.wisc.edu/public/Marinette_Municipalities_2014.zip\",\"http://www.isotc211.org/schemas/2005/gmd/\":\"https://gisdata.wisc.edu/public/metadata/Marinette_Municipalities_2014.xml\"}",
  "b1g_image_ss": ""
}