{
  "geoblacklight_version": "1.0",
  "dc_rights_s": "Public",
  "layer_modified_dt": "2020-01-30T17:05:08Z",
  "dc_identifier_s": "D07E2E90-4DB8-4AB6-9331-DA6A389B5C15",
  "dc_title_s": "Parcels: Kewaunee County, Wisconsin, 2011",
  "dc_description_s": "This data layer represents parcels for Kewaunee County, Wisconsin in 2011.",
  "dc_creator_sm": [
    "Kewaunee County, Wisconsin"
  ],
  "dc_publisher_sm": [
    ""
  ],
  "dc_subject_sm": [
    "Planning and Cadastral"
  ],
  "dc_format_s": "Shapefile",
  "layer_geom_type_s": "Polygon",
  "dct_provenance_s": "Wisconsin",
  "dct_issued_s": "",
  "dct_temporal_sm": [
    "2011"
  ],
  "solr_year_i": "2011",
  "dct_spatial_sm": [
    "Kewaunee County, Wisconsin",
    "Wisconsin"
  ],
  "solr_geom": "ENVELOPE(-87.774447,-87.376468,44.683298,44.319692)",
  "dc_language_sm": [
    "English"
  ],
  "b1g_code_s": "10d",
  "dct_references_s": "{\"http://schema.org/downloadUrl\":\"https://gisdata.wisc.edu/public/Kewaunee_Parcels_2011.zip\",\"http://www.isotc211.org/schemas/2005/gmd/\":\"https://gisdata.wisc.edu/public/metadata/Kewaunee_Parcels_2011.xml\"}",
  "b1g_image_ss": ""
}