{
  "geoblacklight_version": "1.0",
  "dc_rights_s": "Public",
  "layer_modified_dt": "2020-01-30T16:02:12Z",
  "dc_identifier_s": "b5561539-b930-43a1-b648-5db64c967beb",
  "dc_title_s": "Plan of Fort Donelson and outworks",
  "dc_description_s": "Scale 1:7,200. 600 ft. to 1 in.; 1 map; 51 x 43 cm Fort Donelson (Tenn.)--History--Maps",
  "dc_creator_sm": [
    "McPherson, James Birdseye, 1828-1864."
  ],
  "dc_publisher_sm": [
    ""
  ],
  "dc_subject_sm": [
    ""
  ],
  "dc_format_s": "JPEG",
  "layer_geom_type_s": "Image",
  "dct_provenance_s": "Penn State",
  "dct_issued_s": "",
  "dct_temporal_sm": [
    ""
  ],
  "solr_year_i": "9999",
  "dct_spatial_sm": [
    "Tennessee"
  ],
  "solr_geom": "ENVELOPE(-87.89416667,-87.83027778,36.49583333,36.46888889)",
  "dc_language_sm": [
    "English"
  ],
  "b1g_code_s": "08d-01",
  "b1g_image_ss": "",
  "dct_references_s": "{\"http://iiif.io/api/presentation#manifest\":\"https://digital.libraries.psu.edu/iiif/info/maps1/30168/manifest.json\",\"http://schema.org/url\":\"https://collection1.libraries.psu.edu/cdm/ref/collection/maps1/id/30168\"}"
}