{
"layer_geom_type_s": "Point", 
"layer_modified_dt": "2017-05-24T17:31:29Z", 
"solr_geom": "ENVELOPE(-77.114031, -76.911023, 38.992864, 38.818902)", 
"dct_references_s": "{\"http://schema.org/url\":\"http://opendata.dc.gov/datasets/aab075ac11e9415fb329fb4fab970bc3_1\",\"http://schema.org/downloadUrl\":\"http://opendata.dc.gov/datasets/aab075ac11e9415fb329fb4fab970bc3_1.zip\",\"urn:x-esri:serviceType:ArcGIS#DynamicMapLayer\":\"https://maps2.dcgis.dc.gov/dcgis/rest/services/DCGIS_DATA/Violations_Parking_2015/MapServer/1\",\"http://www.isotc211.org/schemas/2005/gmd/\":\"https://opengeometadata.github.io/big-ten/7a/e3/bf/69dc734d98957f87102b7ea49c/iso19139.xml\"}", 
"dc_rights_s": "Public", 
"uuid": "7ae3bf69-dc73-4d98-957f-87102b7ea49c", 
"dct_provenance_s": "Maryland", 
"dc_subject_sm": [
"Transportation", 
"Vision Zero", 
"Public works", 
"Police", 
"Enforcement", 
"Parking", 
"Parking violation", 
"Parking enforcement"
], 
"dct_temporal_sm": "2015", 
"dc_description_s": "Parking citation locations in the District of Columbia. The Vision Zero data contained in this layer pertain to parking violations issued by the District of Columbia's Metropolitan Police Department (MPD) and partner agencies with the authority. For example Parking violation locations are summarized ticket counts based on time of dayData was originally downloaded from the District Department of Motor Vehicle's eTIMS meter work order management system. Data was exported into DDOT\u2019s SQL server Data was then visualized using the street segment centroid coordinates.", 
"dct_issued_s": "2017-03-03", 
"dc_format_s": "Shapefile", 
"dc_type_s": "Dataset", 
"dc_identifier_s": "7ae3bf69-dc73-4d98-957f-87102b7ea49c", 
"georss_polygon_s": "38.818902 -77.114031 38.992864 -77.114031 38.992864 -76.911023 38.818902 -76.911023 38.818902 -77.114031", 
"solr_year_i": 2015, 
"dct_spatial_sm": [
"Washington, District of Columbia, United States"
], 
"dc_publisher_sm": [
"District of Columbia GIS Program"
], 
"layer_id_s": "aab075ac11e9415fb329fb4fab970bc3_1", 
"georss_box_s": "38.818902 -77.114031 38.992864 -76.911023", 
"dc_title_s": "Parking Violations: Washington, D.C., February 2015", 
"layer_slug_s": "7ae3bf69-dc73-4d98-957f-87102b7ea49c", 
"dct_isPartOf_sm": "District of Columbia Open Data"
}