{
  "geoblacklight_version": "1.0",
  "dc_rights_s": "Public",
  "layer_modified_dt": "2020-01-30T16:02:12Z",
  "dc_identifier_s": "5a389c9f-2164-4c51-b0ec-7787b298124f",
  "dc_title_s": "Catawissa, Pennsylvania, 1907",
  "dc_description_s": "Catawissa, Columbia Co., PA, April 1907. 1 map on 4 sheets : col. ; on sheets 65 x 54 cm.  Scale approximately 1:600. 50 ft. to an in.",
  "dc_creator_sm": [
    "Sanborn Map Company"
  ],
  "dc_publisher_sm": [
    "Sanborn Map Company"
  ],
  "dc_subject_sm": [
    "Fire insurance maps"
  ],
  "dc_format_s": "JPEG",
  "layer_geom_type_s": "Image",
  "dct_provenance_s": "Penn State",
  "dct_issued_s": "",
  "dct_temporal_sm": [
    "1907"
  ],
  "solr_year_i": "1907",
  "dct_spatial_sm": [
    "Catawissa, Pennsylvania",
    "Columbia County, Pennsylvania",
    "Pennsylvania"
  ],
  "solr_geom": "ENVELOPE(-76.4689931,-76.452269,40.961949,40.945532)",
  "dc_language_sm": [
    "English"
  ],
  "b1g_code_s": "08d-02",
  "b1g_image_ss": "",
  "dct_references_s": "{\"http://iiif.io/api/presentation#manifest\":\"https://digital.libraries.psu.edu/iiif/info/maps1/5434/manifest.json\",\"http://schema.org/url\":\"https://collection1.libraries.psu.edu/cdm/ref/collection/maps1/id/5434\"}"
}