{
"layer_geom_type_s": "Mixed", 
"layer_modified_dt": "2016-08-02T17:07:27Z", 
"solr_geom": "ENVELOPE(-77.957686, -77.862389, 40.698311, 40.610698)", 
"dct_references_s": "{\"http://schema.org/url\":\"http://www.pasda.psu.edu/uci/DataSummary.aspx?dataset=244\",\"http://www.isotc211.org/schemas/2005/gmd/\":\"https://opengeometadata.github.io/big-ten/1a/27/bd/1a957241b686bce26e3626f9c4/iso19139.xml\"}", 
"dc_rights_s": "Public", 
"uuid": "1a27bd1a-9572-41b6-86bc-e26e3626f9c4", 
"dct_provenance_s": "Penn State", 
"dc_subject_sm": [
"Environment", 
"Biota", 
"Inland Waters", 
"Lakes"
], 
"dc_format_s": "File", 
"dc_description_s": "various datasets on the Stone Valley Experimental Forest, managed by The Pennsylvania State University. Data inculdes: roads, contours, lakes, ponds, hydrology, landuse", 
"dct_temporal_sm": "2000", 
"dc_creator_sm": [
"The Pennsylvania State University"
], 
"dc_type_s": "Dataset", 
"dc_identifier_s": "1a27bd1a-9572-41b6-86bc-e26e3626f9c4", 
"georss_polygon_s": "40.610698 -77.957686 40.698311 -77.957686 40.698311 -77.862389 40.610698 -77.862389 40.610698 -77.957686", 
"solr_year_i": 2000, 
"dct_spatial_sm": [
"Pennsylvania, United States"
], 
"layer_id_s": "1a27bd1a-9572-41b6-86bc-e26e3626f9c4", 
"georss_box_s": "40.610698 -77.957686 40.698311 -77.862389", 
"dc_title_s": "Stone Valley Experimental Forest: Pennsylvania, 2000", 
"layer_slug_s": "1a27bd1a-9572-41b6-86bc-e26e3626f9c4", 
"dct_isPartOf_sm": "Pennsylvania Spatial Data Access (PASDA)"
}