<gmd:MD_Metadata xmlns:gmd="http://www.isotc211.org/2005/gmd" xmlns:geonet="http://www.fao.org/geonetwork" xmlns:csw="http://www.opengis.net/cat/csw/2.0.2">
    <gmd:fileIdentifier>
      <gco:CharacterString xmlns:gco="http://www.isotc211.org/2005/gco">a1e4af9e-289e-41e2-9bfe-89acdff7503a</gco:CharacterString>
    </gmd:fileIdentifier>
    <gmd:language>
      <gmd:LanguageCode codeList="http://www.loc.gov/standards/iso639-2/" codeListValue="eng" codeSpace="ISO639-2"/>
    </gmd:language>
    <gmd:characterSet>
      <gmd:MD_CharacterSetCode codeList="http://standards.iso.org/ittf/PubliclyAvailableStandards/ISO_19139_Schemas/resources/codelist/ML_gmxCodelists.xml#MD_CharacterSetCode" codeListValue="utf8" codeSpace="ISOTC211/19115"/>
    </gmd:characterSet>
    <gmd:hierarchyLevel>
      <gmd:MD_ScopeCode codeList="http://standards.iso.org/ittf/PubliclyAvailableStandards/ISO_19139_Schemas/resources/codelist/ML_gmxCodelists.xml#MD_ScopeCode" codeListValue="dataset" codeSpace="ISOTC211/19115"/>
    </gmd:hierarchyLevel>
    <gmd:hierarchyLevelName>
      <gco:CharacterString xmlns:gco="http://www.isotc211.org/2005/gco">dataset</gco:CharacterString>
    </gmd:hierarchyLevelName>
    <gmd:contact>
      <gmd:CI_ResponsibleParty>
        <gmd:individualName>
          <gco:CharacterString xmlns:gco="http://www.isotc211.org/2005/gco">GIS Librarian</gco:CharacterString>
        </gmd:individualName>
        <gmd:organisationName>
          <gco:CharacterString xmlns:gco="http://www.isotc211.org/2005/gco">Iowa Geological Survey, DNR</gco:CharacterString>
        </gmd:organisationName>
        <gmd:contactInfo>
          <gmd:CI_Contact>
            <gmd:phone>
              <gmd:CI_Telephone>
                <gmd:voice>
                  <gco:CharacterString xmlns:gco="http://www.isotc211.org/2005/gco">319-335-1353</gco:CharacterString>
                </gmd:voice>
              </gmd:CI_Telephone>
            </gmd:phone>
            <gmd:address>
              <gmd:CI_Address>
                <gmd:deliveryPoint>
                  <gco:CharacterString xmlns:gco="http://www.isotc211.org/2005/gco">109 Trowbridge Hall</gco:CharacterString>
                </gmd:deliveryPoint>
                <gmd:city>
                  <gco:CharacterString xmlns:gco="http://www.isotc211.org/2005/gco">Iowa City</gco:CharacterString>
                </gmd:city>
                <gmd:administrativeArea>
                  <gco:CharacterString xmlns:gco="http://www.isotc211.org/2005/gco">IA</gco:CharacterString>
                </gmd:administrativeArea>
                <gmd:postalCode>
                  <gco:CharacterString xmlns:gco="http://www.isotc211.org/2005/gco">52242-1319</gco:CharacterString>
                </gmd:postalCode>
                <gmd:electronicMailAddress>
                  <gco:CharacterString xmlns:gco="http://www.isotc211.org/2005/gco">gis_library@igsb.uiowa.edu</gco:CharacterString>
                </gmd:electronicMailAddress>
              </gmd:CI_Address>
            </gmd:address>
          </gmd:CI_Contact>
        </gmd:contactInfo>
        <gmd:role>
          <gmd:CI_RoleCode codeList="http://standards.iso.org/ittf/PubliclyAvailableStandards/ISO_19139_Schemas/resources/codelist/ML_gmxCodelists.xml#CI_RoleCode" codeListValue="pointOfContact" codeSpace="ISOTC211/19115"/>
        </gmd:role>
      </gmd:CI_ResponsibleParty>
    </gmd:contact>
    <gmd:dateStamp>
      <gco:DateTime xmlns:gco="http://www.isotc211.org/2005/gco">2017-04-05T13:35:10</gco:DateTime>
    </gmd:dateStamp>
    <gmd:metadataStandardName>
      <gco:CharacterString xmlns:gco="http://www.isotc211.org/2005/gco">ISO 19139 Geographic Information - Metadata - Implementation Specification</gco:CharacterString>
    </gmd:metadataStandardName>
    <gmd:metadataStandardVersion>
      <gco:CharacterString xmlns:gco="http://www.isotc211.org/2005/gco">2007</gco:CharacterString>
    </gmd:metadataStandardVersion>
    <gmd:spatialRepresentationInfo>
      <gmd:MD_VectorSpatialRepresentation>
        <gmd:topologyLevel>
          <gmd:MD_TopologyLevelCode codeList="http://standards.iso.org/ittf/PubliclyAvailableStandards/ISO_19139_Schemas/resources/codelist/ML_gmxCodelists.xml#MD_TopologyLevelCode" codeListValue="geometryOnly" codeSpace="ISOTC211/19115"/>
        </gmd:topologyLevel>
        <gmd:geometricObjects>
          <gmd:MD_GeometricObjects>
            <gmd:geometricObjectType>
              <gmd:MD_GeometricObjectTypeCode codeList="http://standards.iso.org/ittf/PubliclyAvailableStandards/ISO_19139_Schemas/resources/codelist/ML_gmxCodelists.xml#MD_GeometricObjectTypeCode" codeListValue="point" codeSpace="ISOTC211/19115"/>
            </gmd:geometricObjectType>
            <gmd:geometricObjectCount>
              <gco:Integer xmlns:gco="http://www.isotc211.org/2005/gco">166</gco:Integer>
            </gmd:geometricObjectCount>
          </gmd:MD_GeometricObjects>
        </gmd:geometricObjects>
      </gmd:MD_VectorSpatialRepresentation>
    </gmd:spatialRepresentationInfo>
    <gmd:referenceSystemInfo>
      <gmd:MD_ReferenceSystem>
        <gmd:referenceSystemIdentifier>
          <gmd:RS_Identifier>
            <gmd:code>
              <gco:CharacterString xmlns:gco="http://www.isotc211.org/2005/gco">26915</gco:CharacterString>
            </gmd:code>
            <gmd:codeSpace>
              <gco:CharacterString xmlns:gco="http://www.isotc211.org/2005/gco">EPSG</gco:CharacterString>
            </gmd:codeSpace>
            <gmd:version>
              <gco:CharacterString xmlns:gco="http://www.isotc211.org/2005/gco">8.2.6</gco:CharacterString>
            </gmd:version>
          </gmd:RS_Identifier>
        </gmd:referenceSystemIdentifier>
      </gmd:MD_ReferenceSystem>
    </gmd:referenceSystemInfo>
    <gmd:identificationInfo>
      <gmd:MD_DataIdentification>
        <gmd:citation>
          <gmd:CI_Citation>
            <gmd:title>
              <gco:CharacterString xmlns:gco="http://www.isotc211.org/2005/gco">State Museums: Iowa, 2007</gco:CharacterString>
            </gmd:title>
            <gmd:date xmlns:gco="http://www.isotc211.org/2005/gco" gco:nilReason="missing">
              <gmd:CI_Date>
                <gmd:date>
                  <gco:Date>2007-04</gco:Date>
                </gmd:date>
                <gmd:dateType>
                  <gmd:CI_DateTypeCode codeList="http://standards.iso.org/ittf/PubliclyAvailableStandards/ISO_19139_Schemas/resources/codelist/ML_gmxCodelists.xml#CI_DateTypeCode" codeListValue="publication"/>
                </gmd:dateType>
              </gmd:CI_Date>
            </gmd:date>
            <gmd:edition>
              <gco:CharacterString xmlns:gco="http://www.isotc211.org/2005/gco">20070529</gco:CharacterString>
            </gmd:edition>
            <gmd:identifier>
              <gmd:MD_Identifier>
                <gmd:code>
                  <gco:CharacterString xmlns:gco="http://www.isotc211.org/2005/gco">urn-a1e4af9e-289e-41e2-9bfe-89acdff7503a</gco:CharacterString>
                </gmd:code>
              </gmd:MD_Identifier>
            </gmd:identifier>
            <gmd:citedResponsibleParty>
              <gmd:CI_ResponsibleParty>
                <gmd:organisationName>
                  <gco:CharacterString xmlns:gco="http://www.isotc211.org/2005/gco">Iowa Geological Survey, DNR</gco:CharacterString>
                </gmd:organisationName>
                <gmd:contactInfo>
                  <gmd:CI_Contact>
                    <gmd:address>
                      <gmd:CI_Address>
                        <gmd:deliveryPoint>
                          <gco:CharacterString xmlns:gco="http://www.isotc211.org/2005/gco">Iowa City, Iowa</gco:CharacterString>
                        </gmd:deliveryPoint>
                      </gmd:CI_Address>
                    </gmd:address>
                  </gmd:CI_Contact>
                </gmd:contactInfo>
                <gmd:role>
                  <gmd:CI_RoleCode codeList="http://standards.iso.org/ittf/PubliclyAvailableStandards/ISO_19139_Schemas/resources/codelist/ML_gmxCodelists.xml#CI_RoleCode" codeListValue="publisher" codeSpace="ISOTC211/19115"/>
                </gmd:role>
              </gmd:CI_ResponsibleParty>
            </gmd:citedResponsibleParty>
            <gmd:citedResponsibleParty>
              <gmd:CI_ResponsibleParty>
                <gmd:organisationName>
                  <gco:CharacterString xmlns:gco="http://www.isotc211.org/2005/gco">Iowa Natural Heritage Foundation</gco:CharacterString>
                </gmd:organisationName>
                <gmd:role>
                  <gmd:CI_RoleCode codeList="http://standards.iso.org/ittf/PubliclyAvailableStandards/ISO_19139_Schemas/resources/codelist/ML_gmxCodelists.xml#CI_RoleCode" codeListValue="originator" codeSpace="ISOTC211/19115"/>
                </gmd:role>
              </gmd:CI_ResponsibleParty>
            </gmd:citedResponsibleParty>
            <gmd:presentationForm>
              <gmd:CI_PresentationFormCode codeList="http://standards.iso.org/ittf/PubliclyAvailableStandards/ISO_19139_Schemas/resources/codelist/ML_gmxCodelists.xml#CI_PresentationFormCode" codeListValue="mapDigital" codeSpace="ISOTC211/19115"/>
            </gmd:presentationForm>
            <gmd:collectiveTitle>
              <gco:CharacterString xmlns:gco="http://www.isotc211.org/2005/gco">Iowa Department of Natural Resources (DNR)</gco:CharacterString>
            </gmd:collectiveTitle>
            <gmd:otherCitationDetails>
              <gco:CharacterString xmlns:gco="http://www.isotc211.org/2005/gco">Point</gco:CharacterString>
            </gmd:otherCitationDetails>
          </gmd:CI_Citation>
        </gmd:citation>
        <gmd:abstract>
          <gco:CharacterString xmlns:gco="http://www.isotc211.org/2005/gco">This dataset was created by the Iowa Natural Heritage Foundation in cooperation with state museum association members. It is a statewide distribution of Iowa state museums.</gco:CharacterString>
        </gmd:abstract>
        <gmd:purpose>
          <gco:CharacterString xmlns:gco="http://www.isotc211.org/2005/gco">This digital, geographically referenced data set was developed by the Iowa Department of Natural Resources to carry out agency responsibilities related to management, protection, and development of Iowa's natural resources.</gco:CharacterString>
        </gmd:purpose>
        <gmd:status>
          <gmd:MD_ProgressCode codeList="http://standards.iso.org/ittf/PubliclyAvailableStandards/ISO_19139_Schemas/resources/codelist/ML_gmxCodelists.xml#MD_ProgressCode" codeListValue="completed" codeSpace="ISOTC211/19115"/>
        </gmd:status>
        <gmd:pointOfContact>
          <gmd:CI_ResponsibleParty>
            <gmd:individualName>
              <gco:CharacterString xmlns:gco="http://www.isotc211.org/2005/gco">Andrea Chase</gco:CharacterString>
            </gmd:individualName>
            <gmd:organisationName>
              <gco:CharacterString xmlns:gco="http://www.isotc211.org/2005/gco">Iowa Natural Heritage Foundation</gco:CharacterString>
            </gmd:organisationName>
            <gmd:positionName>
              <gco:CharacterString xmlns:gco="http://www.isotc211.org/2005/gco">Trails Coordinator</gco:CharacterString>
            </gmd:positionName>
            <gmd:contactInfo>
              <gmd:CI_Contact>
                <gmd:phone>
                  <gmd:CI_Telephone>
                    <gmd:voice>
                      <gco:CharacterString xmlns:gco="http://www.isotc211.org/2005/gco">515-288-1846</gco:CharacterString>
                    </gmd:voice>
                    <gmd:facsimile>
                      <gco:CharacterString xmlns:gco="http://www.isotc211.org/2005/gco">515-288-0137</gco:CharacterString>
                    </gmd:facsimile>
                  </gmd:CI_Telephone>
                </gmd:phone>
                <gmd:address>
                  <gmd:CI_Address>
                    <gmd:electronicMailAddress>
                      <gco:CharacterString xmlns:gco="http://www.isotc211.org/2005/gco">achase@inhf.org</gco:CharacterString>
                    </gmd:electronicMailAddress>
                  </gmd:CI_Address>
                </gmd:address>
                <gmd:hoursOfService>
                  <gco:CharacterString xmlns:gco="http://www.isotc211.org/2005/gco">M-F, 8 AM - 4 PM</gco:CharacterString>
                </gmd:hoursOfService>
                <gmd:contactInstructions>
                  <gco:CharacterString xmlns:gco="http://www.isotc211.org/2005/gco">Alternate contact at Iowa DNR is Cam Conrad, 515-281-5843, cam.conrad@dnr.state.ia.us</gco:CharacterString>
                </gmd:contactInstructions>
              </gmd:CI_Contact>
            </gmd:contactInfo>
            <gmd:role>
              <gmd:CI_RoleCode codeList="http://standards.iso.org/ittf/PubliclyAvailableStandards/ISO_19139_Schemas/resources/codelist/ML_gmxCodelists.xml#CI_RoleCode" codeListValue="pointOfContact" codeSpace="ISOTC211/19115"/>
            </gmd:role>
          </gmd:CI_ResponsibleParty>
        </gmd:pointOfContact>
        <gmd:resourceMaintenance>
          <gmd:MD_MaintenanceInformation>
            <gmd:maintenanceAndUpdateFrequency>
              <gmd:MD_MaintenanceFrequencyCode codeList="http://standards.iso.org/ittf/PubliclyAvailableStandards/ISO_19139_Schemas/resources/codelist/ML_gmxCodelists.xml#MD_MaintenanceFrequencyCode" codeListValue="unknown" codeSpace="ISOTC211/19115"/>
            </gmd:maintenanceAndUpdateFrequency>
          </gmd:MD_MaintenanceInformation>
        </gmd:resourceMaintenance>
        <gmd:resourceConstraints>
          <gmd:MD_Constraints>
            <gmd:useLimitation>
              <gco:CharacterString xmlns:gco="http://www.isotc211.org/2005/gco">The development of the coverages in the NRGIS Library represents a major investment of staff time and effort. As a professional responsibility, the Iowa DNR expects to receive proper credit when these GIS coverages are utilized. The Department also expects that the original documentation will remain with any redistribution of these coverages.</gco:CharacterString>
            </gmd:useLimitation>
          </gmd:MD_Constraints>
        </gmd:resourceConstraints>
        <gmd:resourceConstraints>
          <gmd:MD_LegalConstraints>
            <gmd:useLimitation>
              <gco:CharacterString xmlns:gco="http://www.isotc211.org/2005/gco">Although efforts have been made in correcting errors in order to make this information useful to the Department, the Department assumes no responsibility for errors in the information. Similarly, the Department assumes no responsibility for the consequences of inappropriate uses or interpretations of the data made by anyone to whom this data has been made available. The Department bears no responsibility to inform users of any changes made to this data. Anyone using this data is advised that precision implied by the coverage may far exceed actual precision. Comments on this data are invited and the Department would appreciate that documented errors be brought to staff attention.</gco:CharacterString>
            </gmd:useLimitation>
          </gmd:MD_LegalConstraints>
        </gmd:resourceConstraints>
        <gmd:spatialRepresentationType>
          <gmd:MD_SpatialRepresentationTypeCode codeList="http://standards.iso.org/ittf/PubliclyAvailableStandards/ISO_19139_Schemas/resources/codelist/ML_gmxCodelists.xml#MD_SpatialRepresentationTypeCode" codeListValue="vector" codeSpace="ISOTC211/19115"/>
        </gmd:spatialRepresentationType>
        <gmd:language>
          <gmd:LanguageCode codeList="http://www.loc.gov/standards/iso639-2/" codeListValue="eng" codeSpace="ISO639-2"/>
        </gmd:language>
        <gmd:characterSet>
          <gmd:MD_CharacterSetCode codeList="http://standards.iso.org/ittf/PubliclyAvailableStandards/ISO_19139_Schemas/resources/codelist/ML_gmxCodelists.xml#MD_CharacterSetCode" codeListValue="utf8" codeSpace="ISOTC211/19115"/>
        </gmd:characterSet>
        <gmd:topicCategory>
          <gmd:MD_TopicCategoryCode>structure</gmd:MD_TopicCategoryCode>
        </gmd:topicCategory>
        <gmd:environmentDescription>
          <gco:CharacterString xmlns:gco="http://www.isotc211.org/2005/gco">Microsoft Windows 7 Version 6.1 (Build 7601) Service Pack 1; Esri ArcGIS 10.3.0.4322</gco:CharacterString>
        </gmd:environmentDescription>
        <gmd:extent>
          <gmd:EX_Extent>
            <gmd:description>
              <gco:CharacterString xmlns:gco="http://www.isotc211.org/2005/gco">publication date</gco:CharacterString>
            </gmd:description>
            <gmd:temporalElement>
              <gmd:EX_TemporalExtent>
                <gmd:extent>
                  <gml:TimePeriod xmlns:gml="http://www.opengis.net/gml" gml:id="d466876e331a1052958">
                    <gml:beginPosition>2007</gml:beginPosition>
                    <gml:endPosition indeterminatePosition="unknown">2007</gml:endPosition>
                  </gml:TimePeriod>
                </gmd:extent>
              </gmd:EX_TemporalExtent>
            </gmd:temporalElement>
          </gmd:EX_Extent>
        </gmd:extent>
        <gmd:extent>
          <gmd:EX_Extent>
            <gmd:geographicElement>
              <gmd:EX_GeographicBoundingBox>
                <gmd:extentTypeCode>
                  <gco:Boolean xmlns:gco="http://www.isotc211.org/2005/gco">true</gco:Boolean>
                </gmd:extentTypeCode>
                <gmd:westBoundLongitude>
                  <gco:Decimal xmlns:gco="http://www.isotc211.org/2005/gco">-96.454582</gco:Decimal>
                </gmd:westBoundLongitude>
                <gmd:eastBoundLongitude>
                  <gco:Decimal xmlns:gco="http://www.isotc211.org/2005/gco">-90.113886</gco:Decimal>
                </gmd:eastBoundLongitude>
                <gmd:southBoundLatitude>
                  <gco:Decimal xmlns:gco="http://www.isotc211.org/2005/gco">40.58059</gco:Decimal>
                </gmd:southBoundLatitude>
                <gmd:northBoundLatitude>
                  <gco:Decimal xmlns:gco="http://www.isotc211.org/2005/gco">43.461867</gco:Decimal>
                </gmd:northBoundLatitude>
              </gmd:EX_GeographicBoundingBox>
            </gmd:geographicElement>
          </gmd:EX_Extent>
        </gmd:extent>
        <gmd:descriptiveKeywords>
          <gmd:MD_Keywords>
            <gmd:type>
              <gmd:MD_KeywordTypeCode codeList="http://www.isotc211.org/2005/resources/codeList.xml#MD_KeywordTypeCode" codeListValue="place"/>
            </gmd:type>
            <gmd:keyword>
              <gco:CharacterString xmlns:gco="http://www.isotc211.org/2005/gco">Iowa, United States</gco:CharacterString>
            </gmd:keyword>
          </gmd:MD_Keywords>
        </gmd:descriptiveKeywords>
        <gmd:descriptiveKeywords>
          <gmd:MD_Keywords>
            <gmd:type>
              <gmd:MD_KeywordTypeCode codeList="http://www.isotc211.org/2005/resources/codeList.xml#MD_KeywordTypeCode" codeListValue="theme"/>
            </gmd:type>
            <gmd:keyword>
              <gco:CharacterString xmlns:gco="http://www.isotc211.org/2005/gco">Museums</gco:CharacterString>
            </gmd:keyword>
            <gmd:keyword>
              <gco:CharacterString xmlns:gco="http://www.isotc211.org/2005/gco">History</gco:CharacterString>
            </gmd:keyword>
            <gmd:keyword>
              <gco:CharacterString xmlns:gco="http://www.isotc211.org/2005/gco">Facility</gco:CharacterString>
            </gmd:keyword>
          </gmd:MD_Keywords>
        </gmd:descriptiveKeywords>
      </gmd:MD_DataIdentification>
    </gmd:identificationInfo>
    <gmd:distributionInfo>
      <gmd:MD_Distribution>
        <gmd:distributionFormat>
          <gmd:MD_Format>
            <gmd:name>
              <gco:CharacterString xmlns:gco="http://www.isotc211.org/2005/gco">Shapefile</gco:CharacterString>
            </gmd:name>
          </gmd:MD_Format>
        </gmd:distributionFormat>
        <gmd:distributor>
          <gmd:MD_Distributor>
            <gmd:distributorContact>
              <gmd:CI_ResponsibleParty>
                <gmd:individualName>
                  <gco:CharacterString xmlns:gco="http://www.isotc211.org/2005/gco">GIS Librarian</gco:CharacterString>
                </gmd:individualName>
                <gmd:organisationName>
                  <gco:CharacterString xmlns:gco="http://www.isotc211.org/2005/gco">Iowa Geological Survey, DNR</gco:CharacterString>
                </gmd:organisationName>
                <gmd:contactInfo>
                  <gmd:CI_Contact>
                    <gmd:phone>
                      <gmd:CI_Telephone>
                        <gmd:voice>
                          <gco:CharacterString xmlns:gco="http://www.isotc211.org/2005/gco">319-335-1353</gco:CharacterString>
                        </gmd:voice>
                      </gmd:CI_Telephone>
                    </gmd:phone>
                    <gmd:address>
                      <gmd:CI_Address>
                        <gmd:deliveryPoint>
                          <gco:CharacterString xmlns:gco="http://www.isotc211.org/2005/gco">109 Trowbridge Hall</gco:CharacterString>
                        </gmd:deliveryPoint>
                        <gmd:city>
                          <gco:CharacterString xmlns:gco="http://www.isotc211.org/2005/gco">Iowa City</gco:CharacterString>
                        </gmd:city>
                        <gmd:administrativeArea>
                          <gco:CharacterString xmlns:gco="http://www.isotc211.org/2005/gco">IA</gco:CharacterString>
                        </gmd:administrativeArea>
                        <gmd:postalCode>
                          <gco:CharacterString xmlns:gco="http://www.isotc211.org/2005/gco">52242</gco:CharacterString>
                        </gmd:postalCode>
                        <gmd:electronicMailAddress>
                          <gco:CharacterString xmlns:gco="http://www.isotc211.org/2005/gco">gis_library@igsb.uiowa.edu</gco:CharacterString>
                        </gmd:electronicMailAddress>
                      </gmd:CI_Address>
                    </gmd:address>
                  </gmd:CI_Contact>
                </gmd:contactInfo>
                <gmd:role>
                  <gmd:CI_RoleCode codeList="http://standards.iso.org/ittf/PubliclyAvailableStandards/ISO_19139_Schemas/resources/codelist/ML_gmxCodelists.xml#CI_RoleCode" codeListValue="distributor" codeSpace="ISOTC211/19115"/>
                </gmd:role>
              </gmd:CI_ResponsibleParty>
            </gmd:distributorContact>
          </gmd:MD_Distributor>
        </gmd:distributor>
        <gmd:distributor>
          <gmd:MD_Distributor>
            <gmd:distributorContact>
              <gmd:CI_ResponsibleParty>
                <gmd:organisationName>
                  <gco:CharacterString xmlns:gco="http://www.isotc211.org/2005/gco">Iowa Department of Natural Resources</gco:CharacterString>
                </gmd:organisationName>
                <gmd:positionName>
                  <gco:CharacterString xmlns:gco="http://www.isotc211.org/2005/gco">IMS Administrator</gco:CharacterString>
                </gmd:positionName>
                <gmd:contactInfo>
                  <gmd:CI_Contact>
                    <gmd:phone>
                      <gmd:CI_Telephone>
                        <gmd:voice>
                          <gco:CharacterString xmlns:gco="http://www.isotc211.org/2005/gco">515-281-5843</gco:CharacterString>
                        </gmd:voice>
                      </gmd:CI_Telephone>
                    </gmd:phone>
                    <gmd:address>
                      <gmd:CI_Address>
                        <gmd:electronicMailAddress>
                          <gco:CharacterString xmlns:gco="http://www.isotc211.org/2005/gco">cconrad@dnr.state.ia.us</gco:CharacterString>
                        </gmd:electronicMailAddress>
                      </gmd:CI_Address>
                    </gmd:address>
                  </gmd:CI_Contact>
                </gmd:contactInfo>
                <gmd:role>
                  <gmd:CI_RoleCode codeList="http://standards.iso.org/ittf/PubliclyAvailableStandards/ISO_19139_Schemas/resources/codelist/ML_gmxCodelists.xml#CI_RoleCode" codeListValue="distributor" codeSpace="ISOTC211/19115"/>
                </gmd:role>
              </gmd:CI_ResponsibleParty>
            </gmd:distributorContact>
          </gmd:MD_Distributor>
        </gmd:distributor>
        <gmd:transferOptions>
          <gmd:MD_DigitalTransferOptions>
            <gmd:transferSize>
              <gco:Real xmlns:gco="http://www.isotc211.org/2005/gco">0.005</gco:Real>
            </gmd:transferSize>
            <gmd:onLine>
              <gmd:CI_OnlineResource>
                <gmd:linkage>
                  <gmd:URL>ftp://ftp.igsb.uiowa.edu/gis_library/ia_state/infrastructure/facilities/museum.zip</gmd:URL>
                </gmd:linkage>
                <gmd:protocol>
                  <gco:CharacterString xmlns:gco="http://www.isotc211.org/2005/gco">WWW:DOWNLOAD-1.0-ftp--download</gco:CharacterString>
                </gmd:protocol>
              </gmd:CI_OnlineResource>
            </gmd:onLine>
            <gmd:onLine>
              <gmd:CI_OnlineResource>
                <gmd:linkage>
                  <gmd:URL>ftp://ftp.igsb.uiowa.edu/gis_library/IA_State/Infrastructure/</gmd:URL>
                </gmd:linkage>
                <gmd:protocol>
                  <gco:CharacterString xmlns:gco="http://www.isotc211.org/2005/gco">WWW:LINK</gco:CharacterString>
                </gmd:protocol>
              </gmd:CI_OnlineResource>
            </gmd:onLine>
            <gmd:onLine>
              <gmd:CI_OnlineResource>
                <gmd:linkage>
                  <gmd:URL>https://opengeometadata.github.io/big-ten/a1/e4/af/9e289e41e29bfe89acdff7503a/iso19139.xml</gmd:URL>
                </gmd:linkage>
                <gmd:protocol>
                  <gco:CharacterString xmlns:gco="http://www.isotc211.org/2005/gco">metadata</gco:CharacterString>
                </gmd:protocol>
              </gmd:CI_OnlineResource>
            </gmd:onLine>
          </gmd:MD_DigitalTransferOptions>
        </gmd:transferOptions>
      </gmd:MD_Distribution>
    </gmd:distributionInfo>
    <gmd:dataQualityInfo>
      <gmd:DQ_DataQuality>
        <gmd:scope>
          <gmd:DQ_Scope>
            <gmd:level>
              <gmd:MD_ScopeCode codeList="http://standards.iso.org/ittf/PubliclyAvailableStandards/ISO_19139_Schemas/resources/codelist/ML_gmxCodelists.xml#MD_ScopeCode" codeListValue="dataset" codeSpace="ISOTC211/19115"/>
            </gmd:level>
          </gmd:DQ_Scope>
        </gmd:scope>
        <gmd:report>
          <gmd:DQ_AbsoluteExternalPositionalAccuracy>
            <gmd:measureDescription>
              <gco:CharacterString xmlns:gco="http://www.isotc211.org/2005/gco">Geocoded street addresses to get latitude, longitude coordinates for each museum</gco:CharacterString>
            </gmd:measureDescription>
          </gmd:DQ_AbsoluteExternalPositionalAccuracy>
        </gmd:report>
        <gmd:lineage>
          <gmd:LI_Lineage>
            <gmd:processStep>
              <gmd:LI_ProcessStep>
                <gmd:description>
                  <gco:CharacterString xmlns:gco="http://www.isotc211.org/2005/gco">Created point shapefile from latitude and longitude coordinates in Excel spreadsheet. Reprojected points from the Geographic lat/long WGS 1984 projection to UTM NAD 1983 Zone 15N projection.</gco:CharacterString>
                </gmd:description>
              </gmd:LI_ProcessStep>
            </gmd:processStep>
            <gmd:processStep>
              <gmd:LI_ProcessStep>
                <gmd:description>
                  <gco:CharacterString xmlns:gco="http://www.isotc211.org/2005/gco">Geocoded street addresses for each museum to get latitude and longitude coordinates, which were entered into Excel spreadsheet.</gco:CharacterString>
                </gmd:description>
              </gmd:LI_ProcessStep>
            </gmd:processStep>
          </gmd:LI_Lineage>
        </gmd:lineage>
      </gmd:DQ_DataQuality>
    </gmd:dataQualityInfo>
  </gmd:MD_Metadata>
  